thread_factory/__author__.py
thread_factory/__init__.py
thread_factory/__version__.py
thread_factory/concurrency/__init__.py
thread_factory/concurrency/concurrent_bag.py
thread_factory/concurrency/concurrent_buffer.py
thread_factory/concurrency/concurrent_collection.py
thread_factory/concurrency/concurrent_dictionary.py
thread_factory/concurrency/concurrent_list.py
thread_factory/concurrency/concurrent_queue.py
thread_factory/concurrency/concurrent_set.py
thread_factory/concurrency/concurrent_stack.py
thread_factory/concurrency/sync_types/__init__.py
thread_factory/concurrency/sync_types/sync_bool.py
thread_factory/concurrency/sync_types/sync_float.py
thread_factory/concurrency/sync_types/sync_int.py
thread_factory/concurrency/sync_types/sync_ref.py
thread_factory/concurrency/sync_types/sync_string.py
thread_factory/synchronization/__init__.py
thread_factory/synchronization/controllers/__init__.py
thread_factory/synchronization/controllers/signal_controller.py
thread_factory/synchronization/coordinators/__init__.py
thread_factory/synchronization/coordinators/clock_barrier.py
thread_factory/synchronization/coordinators/conductor.py
thread_factory/synchronization/coordinators/multi_conductor.py
thread_factory/synchronization/coordinators/scout.py
thread_factory/synchronization/coordinators/transit_barrier.py
thread_factory/synchronization/dispatchers/__init__.py
thread_factory/synchronization/dispatchers/fork.py
thread_factory/synchronization/dispatchers/signal_fork.py
thread_factory/synchronization/dispatchers/sync_fork.py
thread_factory/synchronization/dispatchers/sync_signal_fork.py
thread_factory/synchronization/execution/__init__.py
thread_factory/synchronization/execution/bypass_conductor.py
thread_factory/synchronization/primitives/__init__.py
thread_factory/synchronization/primitives/dynaphore.py
thread_factory/synchronization/primitives/flow_regulator.py
thread_factory/synchronization/primitives/latch.py
threadfactory-1.5.2.dist-info/licenses/LICENSE
threadfactory-1.5.2.dist-info/licenses/NOTICE
threadfactory-1.5.2.dist-info/METADATA
threadfactory-1.5.2.dist-info/WHEEL
threadfactory-1.5.2.dist-info/top_level.txt
threadfactory-1.5.2.dist-info/RECORD
