Metadata-Version: 2.4
Name: threadfactory
Version: 1.5.2
Summary: High-performance thread-safe (No-GIL–friendly) data structures and parallel operations for Python 3.13+.
Author-email: Mark Geleta <SynapticAISystems@gmail.com>
Maintainer-email: Mark Geleta <SynapticAISystems@gmail.com>
License-Expression: Apache-2.0
Project-URL: Homepage, https://github.com/Synaptic724/ThreadFactory
Project-URL: Repository, https://github.com/Synaptic724/ThreadFactory
Project-URL: Issues, https://github.com/Synaptic724/ThreadFactory/issues
Project-URL: Documentation, https://threadfactory.readthedocs.io/en/latest/
Project-URL: LinkedIn, https://www.linkedin.com/in/mark-geleta-4b59b752/
Keywords: concurrency,parallelism,thread-safe,no-GIL,threading,parallel processing,concurrent collections,multithreading,high-performance,python concurrency,free-threading,thread factory,ThreadFactory
Classifier: Programming Language :: Python :: 3
Classifier: Programming Language :: Python :: 3.13
Classifier: Programming Language :: Python :: Implementation :: CPython
Classifier: Operating System :: OS Independent
Classifier: Intended Audience :: Developers
Classifier: Intended Audience :: Science/Research
Classifier: Topic :: Software Development :: Libraries :: Python Modules
Classifier: Topic :: Software Development :: Libraries
Classifier: Topic :: System :: Distributed Computing
Classifier: Topic :: System :: Networking
Classifier: Topic :: Utilities
Classifier: Environment :: Console
Requires-Python: >=3.13
License-File: LICENSE
License-File: NOTICE
Requires-Dist: python-ulid>=3.0.0
Dynamic: license-file
